django_hierarkey-2.0.0.dist-info/licenses/AUTHORS
django_hierarkey-2.0.0.dist-info/licenses/LICENSE
hierarkey/__init__.py
hierarkey/forms.py
hierarkey/models.py
hierarkey/proxy.py
hierarkey/utils.py
django_hierarkey-2.0.0.dist-info/METADATA
django_hierarkey-2.0.0.dist-info/WHEEL
django_hierarkey-2.0.0.dist-info/top_level.txt
django_hierarkey-2.0.0.dist-info/RECORD
