Metadata-Version: 2.4
Name: django-hierarkey
Version: 2.0.0
Summary: Hierarchical key-value store for django
Home-page: https://github.com/raphaelm/django-hierarkey
Author: Raphael Michel
Author-email: mail@raphaelmichel.de
License: Apache License 2.0
Keywords: strings database models keyvalue
Classifier: Intended Audience :: Developers
Classifier: Intended Audience :: Other Audience
Classifier: License :: OSI Approved :: Apache Software License
Classifier: Programming Language :: Python :: 3.9
Classifier: Programming Language :: Python :: 3.10
Classifier: Programming Language :: Python :: 3.11
Classifier: Framework :: Django :: 4.2
Classifier: Framework :: Django :: 5.0
Classifier: Framework :: Django :: 5.1
Classifier: Framework :: Django :: 5.2
License-File: LICENSE
License-File: AUTHORS
Requires-Dist: python-dateutil
Dynamic: author
Dynamic: author-email
Dynamic: classifier
Dynamic: description
Dynamic: home-page
Dynamic: keywords
Dynamic: license
Dynamic: license-file
Dynamic: requires-dist
Dynamic: summary
